phys/__init__.py
phys/cosmic_ray/__init__.py
phys/cosmic_ray/crdb.py
phys/cosmic_ray/tools.py
phys/cosmic_ray/air_shower/__init__.py
phys/cosmic_ray/air_shower/analytical.py
phys/cosmic_ray/air_shower/gaisser_hillas.py
phys/cosmic_ray/air_shower/lafebre.py
phys/cosmic_ray/air_shower/nerling.py
phys/cosmic_ray/data/__init__.py
phys/cosmic_ray/data/convert_galprop_format.py
phys/cosmic_ray/data/convert_webplotdigitizer_csv.py
phys/cosmic_ray/data/parse_txt.py
phys/cosmic_ray/data/parse_xml.py
phys/cosmic_ray/fluxes/__init__.py
phys/cosmic_ray/fluxes/elbert.py
phys/cosmic_ray/fluxes/gaisser.py
phys/cosmic_ray/fluxes/gst.py
phys/cosmic_ray/fluxes/hoerandel.py
phys/cosmic_ray/fluxes/muon_flux.py
phys_cosmic_ray-0.1.2.dist-info/METADATA
phys_cosmic_ray-0.1.2.dist-info/RECORD
phys_cosmic_ray-0.1.2.dist-info/WHEEL
phys_cosmic_ray-0.1.2.dist-info/top_level.txt
