Metadata-Version: 2.1
Name: phys-cosmic-ray
Version: 0.1.2
Summary: Some code related to cosmic ray physics.
Home-page: https://github.com/javierggt/phys-cosmic-ray
Author: Javier G. Gonzalez
Author-email: javierggt@yahoo.com
License: UNKNOWN
Keywords: physics cosmic rays
Platform: UNKNOWN
Classifier: Development Status :: 3 - Alpha
Classifier: Intended Audience :: Education
Classifier: Intended Audience :: Science/Research
Classifier: Topic :: Scientific/Engineering :: Physics
Classifier: License :: OSI Approved :: MIT License
Classifier: Programming Language :: Python :: 2
Classifier: Programming Language :: Python :: 2.7
Classifier: Programming Language :: Python :: 3.7
Requires-Dist: phys
Requires-Dist: numpy
Requires-Dist: scipy
